okayhold/__init__.py
okayhold/core/OkayDict.py
okayhold/core/OkayList.py
okayhold/core/OkayObject.py
okayhold/core/OkaySet.py
okayhold/core/__init__.py
okayhold/tests/__init__.py
okayhold/tests/test_dict.py
okayhold/tests/test_doc.py
okayhold/tests/test_list.py
okayhold/tests/test_set.py
okayhold-0.3.0.dist-info/licenses/LICENSE.txt
okayhold-0.3.0.dist-info/METADATA
okayhold-0.3.0.dist-info/WHEEL
okayhold-0.3.0.dist-info/top_level.txt
okayhold-0.3.0.dist-info/RECORD
