Metadata-Version: 2.4
Name: okayhold
Version: 0.3.0
Summary: This project provides mutable collection types with a data property and common sense implementations of certain methods.
Author-email: Johannes <johannes.programming@gmail.com>
License: The MIT License (MIT)
Project-URL: Download, https://pypi.org/project/okayhold/#files
Project-URL: Index, https://pypi.org/project/okayhold/
Project-URL: Source, https://github.com/johannes-programming/okayhold/
Project-URL: Website, https://okayhold.johannes-programming.online/
Classifier: Development Status :: 3 - Alpha
Classifier: License :: OSI Approved :: MIT License
Classifier: Natural Language :: English
Classifier: Operating System :: OS Independent
Classifier: Programming Language :: Python
Classifier: Programming Language :: Python :: 3
Classifier: Programming Language :: Python :: 3 :: Only
Classifier: Typing :: Typed
Requires-Python: >=3.11
License-File: LICENSE.txt
Requires-Dist: cmp3<1,>=0.5.1
Requires-Dist: datahold<3,>=2.3a2
Requires-Dist: datarepr<2,>=1.1.0
Requires-Dist: frozendict<3,>=2.4.6
Requires-Dist: scaevola<2,>=1.1.1
Requires-Dist: setdoc<2,>=1.2.8
Dynamic: license-file
